torchscale/__init__.py
torchscale/architecture/__init__.py
torchscale/architecture/config.py
torchscale/architecture/decoder.py
torchscale/architecture/encoder.py
torchscale/architecture/encoder_decoder.py
torchscale/architecture/retnet.py
torchscale/architecture/utils.py
torchscale/component/__init__.py
torchscale/component/dilated_attention.py
torchscale/component/droppath.py
torchscale/component/embedding.py
torchscale/component/feedforward_network.py
torchscale/component/flash_attention.py
torchscale/component/gate_linear_unit.py
torchscale/component/multihead_attention.py
torchscale/component/multiscale_retention.py
torchscale/component/multiway_network.py
torchscale/component/relative_position_bias.py
torchscale/component/rms_norm.py
torchscale/component/utils.py
torchscale/component/xpos_relative_position.py
torchscale/component/xmoe/__init__.py
torchscale/component/xmoe/global_groups.py
torchscale/component/xmoe/moe_layer.py
torchscale/component/xmoe/routing.py
torchscale/model/BEiT3.py
torchscale/model/LongNet.py
torchscale/model/__init__.py
torchscale_gml-0.2.3.dist-info/LICENSE
torchscale_gml-0.2.3.dist-info/METADATA
torchscale_gml-0.2.3.dist-info/WHEEL
torchscale_gml-0.2.3.dist-info/top_level.txt
torchscale_gml-0.2.3.dist-info/RECORD
